viihdexdl/__init__.py
viihdexdl/__main__.py
viihdexdl-0.17.post1.dist-info/LICENSE
viihdexdl-0.17.post1.dist-info/METADATA
viihdexdl-0.17.post1.dist-info/WHEEL
viihdexdl-0.17.post1.dist-info/entry_points.txt
viihdexdl-0.17.post1.dist-info/top_level.txt
viihdexdl-0.17.post1.dist-info/RECORD
