Metadata-Version: 2.1
Name: viihdexdl
Version: 0.17.post1
Summary: Command line tool for downloading HLS streams with FFmpeg
Home-page: https://github.com/Qotscha/viihdexdl
Author: Qotscha
Classifier: Development Status :: 3 - Alpha
Classifier: Environment :: Console
Classifier: Environment :: Win32 (MS Windows)
Classifier: License :: OSI Approved :: MIT License
Classifier: Operating System :: Microsoft :: Windows
Classifier: Operating System :: POSIX :: Linux
Classifier: Programming Language :: Python :: 3
License-File: LICENSE
Requires-Dist: requests
Requires-Dist: langcodes
